keyflow/__init__.py
keyflow-1.1.1.dist-info/LICENSE
keyflow-1.1.1.dist-info/METADATA
keyflow-1.1.1.dist-info/WHEEL
keyflow-1.1.1.dist-info/top_level.txt
keyflow-1.1.1.dist-info/RECORD
