Metadata-Version: 2.1
Name: keyflow
Version: 1.1.1
Summary: A small python library to simulate typing in the console and custom text formatting.
Author-email: Aneousion <sanusirry@gmail.com>
Project-URL: Homepage, https://github.com/aneousion/keyflow
Project-URL: Bug Tracker, https://github.com/aneousion/keyflow/issues
Classifier: Programming Language :: Python :: 3
Classifier: License :: OSI Approved :: MIT License
Classifier: Operating System :: OS Independent
Requires-Python: >=3.7
License-File: LICENSE
